vecx_llamaindex/__init__.py
vecx_llamaindex/base.py
vecx_llamaindex-0.1.2.dist-info/METADATA
vecx_llamaindex-0.1.2.dist-info/WHEEL
vecx_llamaindex-0.1.2.dist-info/top_level.txt
vecx_llamaindex-0.1.2.dist-info/RECORD
