Metadata-Version: 2.1
Name: vecx-llamaindex
Version: 0.1.2
Summary: Encrypted Vector Database for Secure and Fast ANN Searches
Home-page: https://vectorxdb.ai
Author: LaunchX Labs
Author-email: vineet@launchxlabs.ai
Classifier: Programming Language :: Python :: 3
Classifier: License :: OSI Approved :: MIT License
Classifier: Operating System :: OS Independent
Requires-Python: >=3.6
Requires-Dist: llama-index>=0.12.34
Requires-Dist: vecx>=0.32.1
